pypalettes/__init__.py
pypalettes/create_cmap.py
pypalettes/deprecated.py
pypalettes/load_cmap.py
pypalettes/load_palette.py
pypalettes/palettes.csv
pypalettes/show_cmap.py
pypalettes/utils.py
pypalettes-0.2.1.dist-info/licenses/LICENSE.note
pypalettes-0.2.1.dist-info/METADATA
pypalettes-0.2.1.dist-info/WHEEL
pypalettes-0.2.1.dist-info/top_level.txt
pypalettes-0.2.1.dist-info/RECORD
