Metadata-Version: 2.4
Name: pypalettes
Version: 0.2.1
Summary: A dependency-free large (+2500) collection of colormaps and palettes for Python.
Author-email: Joseph Barbier <joseph.barbierdarnal@gmail.com>
Project-URL: Homepage, https://python-graph-gallery.com/color-palette-finder/
Project-URL: Issues, https://github.com/y-sunflower/pypalettes/issues
Project-URL: Documentation, https://python-graph-gallery.com/introduction-to-pypalettes/
Project-URL: Repository, https://github.com/y-sunflower/pypalettes
Keywords: palette,colormap,cmap,matplotlib,dataviz,visualization,seaborn,plotly,bokeh,altair
Classifier: Programming Language :: Python :: 3
Classifier: License :: OSI Approved :: MIT License
Classifier: Operating System :: OS Independent
Classifier: Framework :: Matplotlib
Requires-Python: >=3.10
License-File: LICENSE.note
Dynamic: license-file
